[{"model": "authapp.customuser", "pk": 1, "fields": {"password": "pbkdf2_sha256$390000$oLJlrRFL438dk56O2bn4aA$9/Kv3CXv8wKVNdqsWdsJZmdECg9HJqM861ipGWEb+us=", "last_login": "2022-11-21T18:57:02.802Z", "is_superuser": false, "username": "alex", "first_name": "Aleksandr", "last_name": "Reznik", "age": 18, "avatar": "", "email": "sashaaaareznik@gmail.com", "is_staff": false, "is_active": true, "date_joined": "2022-11-18T22:13:00.342Z", "groups": [], "user_permissions": []}}, {"model": "authapp.customuser", "pk": 2, "fields": {"password": "pbkdf2_sha256$390000$mE7UYq7JF7E4BHvXMVCs1b$JuhH/6Ld/5Y6wYR58VZECN2hI2txMyjcGArok3me/NE=", "last_login": "2022-11-26T11:46:24.581Z", "is_superuser": true, "username": "django", "first_name": "", "last_name": "", "age": null, "avatar": "", "email": "django_@gmail.com", "is_staff": true, "is_active": true, "date_joined": "2022-11-18T22:20:34.092Z", "groups": [], "user_permissions": []}}, {"model": "authapp.customuser", "pk": 3, "fields": {"password": "pbkdf2_sha256$390000$gYrJYUei6RhZ3PzDW1pP2Z$ldWMz9YfzrKuoXn/AVlnva6mmzkQi2LVnqHrjd7QK/A=", "last_login": "2022-11-19T14:46:09.750Z", "is_superuser": false, "username": "34", "first_name": "f", "last_name": "f", "age": 18, "avatar": "", "email": "ddf", "is_staff": false, "is_active": true, "date_joined": "2022-11-19T14:34:02.510Z", "groups": [], "user_permissions": []}}]
